trontxsize/__init__.py
trontxsize/tron.proto
trontxsize/tron_pb2.py
trontxsize-1.1.1.dist-info/METADATA
trontxsize-1.1.1.dist-info/WHEEL
trontxsize-1.1.1.dist-info/licenses/LICENSE
trontxsize-1.1.1.dist-info/RECORD
