Metadata-Version: 2.4
Name: trontxsize
Version: 1.1.1
Summary: Calculate tron transaction size (bandwidth)
Project-URL: Homepage, https://github.com/bitcart/trontxsize
Project-URL: Source, https://github.com/bitcart/trontxsize
Project-URL: Changelog, https://github.com/bitcart/trontxsize/blob/master/CHANGELOG.md
Author-email: MrNaif2018 <chuff184@gmail.com>
License-Expression: MIT
License-File: LICENSE
Keywords: bandwidth,bitcart,tron,trx
Classifier: Development Status :: 5 - Production/Stable
Classifier: Intended Audience :: Developers
Classifier: License :: OSI Approved :: MIT License
Classifier: Programming Language :: Python :: 3
Classifier: Programming Language :: Python :: 3.9
Classifier: Programming Language :: Python :: 3.10
Classifier: Programming Language :: Python :: 3.11
Classifier: Programming Language :: Python :: 3.12
Classifier: Programming Language :: Python :: 3.13
Classifier: Topic :: Software Development :: Build Tools
Requires-Python: >=3.9
Requires-Dist: base58
Requires-Dist: protobuf
